{
  "Version": "6.1.7601.23455-AMD64",
  "md5": "15fdbf913380b2887e92ad1b30e2dd1c",
  "InternalName": "apisetstub",
  "CompanyName": "Microsoft Corporation",
  "FileDescription": "ApiSet Stub DLL",
  "FileVersion": "6.1.7601.23455 (win7sp1_ldr.160516-0600)",
  "ProductVersion": "6.1.7601.23455",
  "PeChecksum": 9521,
  "Size": 3584,
  "Machine": "AMD64",
  "exports": [
    {
      "ord": 1,
      "name": "CreateFileMappingW"
    },
    {
      "ord": 2,
      "name": "FlushViewOfFile"
    },
    {
      "ord": 3,
      "name": "MapViewOfFile"
    },
    {
      "ord": 4,
      "name": "MapViewOfFileEx"
    },
    {
      "ord": 5,
      "name": "OpenFileMappingW"
    },
    {
      "ord": 6,
      "name": "ReadProcessMemory"
    },
    {
      "ord": 7,
      "name": "UnmapViewOfFile"
    },
    {
      "ord": 8,
      "name": "VirtualAlloc"
    },
    {
      "ord": 9,
      "name": "VirtualAllocEx"
    },
    {
      "ord": 10,
      "name": "VirtualFree"
    },
    {
      "ord": 11,
      "name": "VirtualFreeEx"
    },
    {
      "ord": 12,
      "name": "VirtualProtect"
    },
    {
      "ord": 13,
      "name": "VirtualProtectEx"
    },
    {
      "ord": 14,
      "name": "VirtualQuery"
    },
    {
      "ord": 15,
      "name": "VirtualQueryEx"
    },
    {
      "ord": 16,
      "name": "WriteProcessMemory"
    }
  ]
}