{
  "Version": "6.1.7600.16385-I386",
  "md5": "4a44c3838cb7724019e18593fe97686a",
  "InternalName": "apisetstub",
  "CompanyName": "Microsoft Corporation",
  "FileDescription": "ApiSet Stub DLL",
  "FileVersion": "6.1.7600.16385 (win7_rtm.090713-1255)",
  "ProductVersion": "6.1.7600.16385",
  "PeChecksum": 54453,
  "Size": 2560,
  "Machine": "I386",
  "exports": [
    {
      "ord": 1,
      "name": "ChangeServiceConfig2W"
    },
    {
      "ord": 2,
      "name": "ChangeServiceConfigW"
    },
    {
      "ord": 3,
      "name": "NotifyServiceStatusChangeW"
    },
    {
      "ord": 4,
      "name": "QueryServiceConfig2W"
    },
    {
      "ord": 5,
      "name": "QueryServiceConfigW"
    },
    {
      "ord": 6,
      "name": "QueryServiceObjectSecurity"
    },
    {
      "ord": 7,
      "name": "QueryServiceStatusEx"
    },
    {
      "ord": 8,
      "name": "SetServiceObjectSecurity"
    }
  ]
}